{
  "kind": "collectionType",
  "collectionName": "invites",
  "info": {
    "singularName": "invite",
    "pluralName": "invites",
    "displayName": "Invite"
  },
  "options": {
    "draftAndPublish": true
  },
  "pluginOptions": {},
  "attributes": {
    "title": {
      "type": "string"
    },
    "description": {
      "type": "text"
    },
    "reaction": {
      "type": "enumeration",
      "default": "pending",
      "enum": [
        "pending",
        "accepted",
        "rejected"
      ]
    },
    "sender": {
      "type": "string",
      "required": true
    },
    "recipient": {
      "type": "string",
      "required": true
    }
  }
}
